{"name":"closeUnbilledPOReceipt","id":"org.icrc.fadapplic.IRIS.FAD.AccountsPayable.UnbilledPOReceipts:closeUnbilledPOReceipt","testCaseName":"org.icrc.fadapplic.IRIS.FAD.AccountsPayable.UnbilledPOReceipts","testSteps":[{"number":1,"description":"Given that I\u0027m logged into \u0027Unbilled PO Receipt\u0027 page","duration":89537,"startTime":"2022-10-20T19:51:10.699+08:00[Asia/Shanghai]","screenshots":[{"screenshot":"3e2ed35f1d91829b3c19aca940a487d0530af0bd24bac1dc6745f47fd7bafb48.png","timeStamp":1666266760236}],"result":"SUCCESS","precondition":false,"level":0,"children":[{"number":2,"description":"When i open FAD URL","duration":84527,"startTime":"2022-10-20T19:51:10.699+08:00[Asia/Shanghai]","screenshots":[{"screenshot":"36b7492998a052c410a309a2b09170f4d6720601df3e520c758b9e260116dbce.png","timeStamp":1666266755226}],"result":"SUCCESS","precondition":false,"level":1},{"number":3,"description":"When i open page from sidebar menu: {Accounts Payable,Unbilled PO Receipts,Close Unbilled PO Receipt}","duration":5000,"startTime":"2022-10-20T19:52:35.227+08:00[Asia/Shanghai]","screenshots":[{"screenshot":"36b7492998a052c410a309a2b09170f4d6720601df3e520c758b9e260116dbce.png","timeStamp":1666266755241},{"screenshot":"9c210859924e1037531832aaead45308e1f3088ad63556cc0df1a50ed6123435.png","timeStamp":1666266755814},{"screenshot":"9aa90a0ccf6d00f76a037c60c906c696745c61eb9a1af257954a35c5ea2d676f.png","timeStamp":1666266756364},{"screenshot":"cb266ae2ba36b59214e77aadbd4a084ea5ea9a7632559c583347eb078ca4b5c4.png","timeStamp":1666266756941},{"screenshot":"3e2ed35f1d91829b3c19aca940a487d0530af0bd24bac1dc6745f47fd7bafb48.png","timeStamp":1666266760227}],"result":"SUCCESS","precondition":false,"level":1}]},{"number":4,"description":"Then the \u0027Unbilled PO Receipts\u0027 page and its contents should show up","duration":240,"startTime":"2022-10-20T19:52:40.236+08:00[Asia/Shanghai]","screenshots":[{"screenshot":"3e2ed35f1d91829b3c19aca940a487d0530af0bd24bac1dc6745f47fd7bafb48.png","timeStamp":1666266760476}],"result":"SUCCESS","precondition":false,"level":0},{"number":5,"description":"When I set the \u0027Supplier\u0027 to \u0027115227\u0027","duration":5125,"startTime":"2022-10-20T19:52:40.477+08:00[Asia/Shanghai]","screenshots":[{"screenshot":"0b84d922167310c74061f29193c7db0ee35481f05561d3202861bbc341c128fb.png","timeStamp":1666266763061},{"screenshot":"d7d300e6c3716ba44b2fc6379829f869843cacc11a6f6cba54bf5892119f8de2.png","timeStamp":1666266765602}],"result":"SUCCESS","precondition":false,"level":0},{"number":6,"description":"When I click on \u0027Search\u0027 button","duration":532,"startTime":"2022-10-20T19:52:45.602+08:00[Asia/Shanghai]","screenshots":[{"screenshot":"cd5ced0a88fbe6cdd580779c9d20d2b323593b0846dd79ddd780bd7214001dd9.png","timeStamp":1666266766125},{"screenshot":"cd5ced0a88fbe6cdd580779c9d20d2b323593b0846dd79ddd780bd7214001dd9.png","timeStamp":1666266766134}],"result":"SUCCESS","precondition":false,"level":0},{"number":7,"description":"Then the \u0027Open Invoices\u0027 search result should show up","duration":1521,"startTime":"2022-10-20T19:52:46.135+08:00[Asia/Shanghai]","screenshots":[{"screenshot":"26d0e48bce081f851cc7f7de994b4be4470b4385f604675472506e6dc63dedce.png","timeStamp":1666266767656}],"result":"SUCCESS","precondition":false,"level":0},{"number":8,"description":"When I select first open invoices row","duration":802,"startTime":"2022-10-20T19:52:47.656+08:00[Asia/Shanghai]","screenshots":[{"screenshot":"a8c144560530ec2a7fc51d08ca0784801df8c1fad2224f217f19b9b98f5cc0c1.png","timeStamp":1666266768446},{"screenshot":"a8c144560530ec2a7fc51d08ca0784801df8c1fad2224f217f19b9b98f5cc0c1.png","timeStamp":1666266768458}],"result":"SUCCESS","precondition":false,"level":0},{"number":9,"description":"When I click \u0027Select CUPR Account\u0027 button","duration":1437,"startTime":"2022-10-20T19:52:48.458+08:00[Asia/Shanghai]","screenshots":[{"screenshot":"78419fc1c1e06e9bf31956695e3bc7b3d4ffbed00facac996c586389d2ba722c.png","timeStamp":1666266769082},{"screenshot":"700b21692109fb44b8c511533c939f5811bcc285377ea9f7f4ec52c4275a9554.png","timeStamp":1666266769895}],"result":"SUCCESS","precondition":false,"level":0},{"number":10,"description":"Then the \u0027Select CUPR Account\u0027 modal should show up","duration":311,"startTime":"2022-10-20T19:52:49.896+08:00[Asia/Shanghai]","screenshots":[{"screenshot":"fd6a1b77c000034ec3543d778d906e7a8e45de1dff734bb9180dab19db58671a.png","timeStamp":1666266770207}],"result":"SUCCESS","precondition":false,"level":0},{"number":11,"description":"When I click first CUPR Account from modal","duration":30812,"startTime":"2022-10-20T19:52:50.207+08:00[Asia/Shanghai]","screenshots":[{"screenshot":"8364b8d02be76617e576e0c6e5c279b9f8c4e770aa9710d272add7cc1bd2b9af.png","timeStamp":1666266801009},{"screenshot":"8364b8d02be76617e576e0c6e5c279b9f8c4e770aa9710d272add7cc1bd2b9af.png","timeStamp":1666266801019}],"result":"SUCCESS","precondition":false,"level":0},{"number":12,"description":"When I click modal \u0027Submit\u0027 button","duration":642,"startTime":"2022-10-20T19:53:21.020+08:00[Asia/Shanghai]","screenshots":[{"screenshot":"f23928330da786f83f24f932f65baaef5e8a64711541acfde4c4e67f7f582598.png","timeStamp":1666266801652},{"screenshot":"f23928330da786f83f24f932f65baaef5e8a64711541acfde4c4e67f7f582598.png","timeStamp":1666266801662}],"result":"SUCCESS","precondition":false,"level":0},{"number":13,"description":"When I click on \u0027Proceed\u0027 button","duration":4011,"startTime":"2022-10-20T19:53:21.662+08:00[Asia/Shanghai]","screenshots":[{"screenshot":"58c03bb6381a011b1f103264fe8b7f56b197ea22add05441741ba406197ad2e8.png","timeStamp":1666266802202},{"screenshot":"0056a01df6258df952cacbbfc2076b5f16854136ba28952d7996702d89e83849.png","timeStamp":1666266805673}],"result":"SUCCESS","precondition":false,"level":0},{"number":14,"description":"Then the \u0027CUPR Payment Successfully Created\u0027 modal should show up","duration":365,"startTime":"2022-10-20T19:53:25.674+08:00[Asia/Shanghai]","screenshots":[{"screenshot":"304b220fb4b39bef289946566ee3f2860426c58f17173de591e733268100d256.png","timeStamp":1666266806039}],"result":"SUCCESS","precondition":false,"level":0},{"number":15,"description":"When I click on \u0027Exit\u0027 button","duration":4131,"startTime":"2022-10-20T19:53:26.040+08:00[Asia/Shanghai]","screenshots":[{"screenshot":"69abe8744c3bc278129d0b4fe1da61df5b54e8c746ca4cab7393f3d6a1b41da8.png","timeStamp":1666266806895},{"screenshot":"42d0f4f67a0c11138570f4b51600ee9ec280846ced0ea75d4bf5d63d83130d4b.png","timeStamp":1666266810171}],"result":"SUCCESS","precondition":false,"level":0},{"number":16,"description":"Given that I\u0027m logged into \u0027Review A/P Entries Payments\u0027 page","duration":21845,"startTime":"2022-10-20T19:53:30.172+08:00[Asia/Shanghai]","screenshots":[{"screenshot":"0782ccada8b94c048977da1a7f5a3c0c25035ce3a2212e565fa70da40fed6f93.png","timeStamp":1666266832017}],"result":"SUCCESS","precondition":false,"level":0,"children":[{"number":17,"description":"When i open FAD URL","duration":16754,"startTime":"2022-10-20T19:53:30.182+08:00[Asia/Shanghai]","screenshots":[{"screenshot":"9f46123f046779ad9f446e6fa26fa3b567e94ac39f7fdebebb42a9be1ca18546.png","timeStamp":1666266826936}],"result":"SUCCESS","precondition":false,"level":1},{"number":18,"description":"When i open page from sidebar menu: {Accounts Payable,Review A/P Entries,Payments}","duration":5071,"startTime":"2022-10-20T19:53:46.936+08:00[Asia/Shanghai]","screenshots":[{"screenshot":"9f46123f046779ad9f446e6fa26fa3b567e94ac39f7fdebebb42a9be1ca18546.png","timeStamp":1666266826951},{"screenshot":"7aad5a11abe07200e546da2f8151598338f00fe983706fcfcdd26956f602570b.png","timeStamp":1666266827573},{"screenshot":"78b73ee406e4692c189cc3b8392563ea0fa21227978434a33097164714278308.png","timeStamp":1666266828136},{"screenshot":"d80d1d093356dfca13038e751e9d6012f34abeb313cfd183bfb6ce44193c2952.png","timeStamp":1666266828714},{"screenshot":"0782ccada8b94c048977da1a7f5a3c0c25035ce3a2212e565fa70da40fed6f93.png","timeStamp":1666266832007}],"result":"SUCCESS","precondition":false,"level":1}]},{"number":19,"description":"Then the\u0027Payments\u0027 search page should show up","duration":238,"startTime":"2022-10-20T19:53:52.018+08:00[Asia/Shanghai]","screenshots":[{"screenshot":"0782ccada8b94c048977da1a7f5a3c0c25035ce3a2212e565fa70da40fed6f93.png","timeStamp":1666266832256}],"result":"SUCCESS","precondition":false,"level":0},{"number":20,"description":"When I set the \u0027Batch Number\u0027 using saved value from an unbilled PO Receipt","duration":647,"startTime":"2022-10-20T19:53:52.257+08:00[Asia/Shanghai]","screenshots":[{"screenshot":"26a0fa8a3a67ab3ab7c01baeaa183e9c41aa4f027c04802602ae19219b12a40d.png","timeStamp":1666266832904}],"result":"SUCCESS","precondition":false,"level":0,"children":[{"number":21,"description":"When I set the \u0027Batch Number\u0027 to \u00275949939\u0027","duration":627,"startTime":"2022-10-20T19:53:52.267+08:00[Asia/Shanghai]","screenshots":[{"screenshot":"26a0fa8a3a67ab3ab7c01baeaa183e9c41aa4f027c04802602ae19219b12a40d.png","timeStamp":1666266832894}],"result":"SUCCESS","precondition":false,"level":1}]},{"number":22,"description":"When I click on \u0027Search\u0027 button","duration":2090,"startTime":"2022-10-20T19:53:52.904+08:00[Asia/Shanghai]","screenshots":[{"screenshot":"54606d81e3ccf516f69a6748f7d49fb2750735e49218e4d5f6274c616a301760.png","timeStamp":1666266833431},{"screenshot":"acc959c069bd5f126120fdafd1bc18700afcf2ae7d8df215f96ef692b9de603a.png","timeStamp":1666266834994}],"result":"SUCCESS","precondition":false,"level":0},{"number":23,"description":"When I click on \u0027Delete\u0027 button","duration":516,"startTime":"2022-10-20T19:53:54.994+08:00[Asia/Shanghai]","screenshots":[{"screenshot":"dee98a2566522da7dfb7afc78de1c4485ef7e841b363eca6692777aad515b172.png","timeStamp":1666266835501},{"screenshot":"dee98a2566522da7dfb7afc78de1c4485ef7e841b363eca6692777aad515b172.png","timeStamp":1666266835510}],"result":"SUCCESS","precondition":false,"level":0},{"number":24,"description":"Then the \u0027Delete Manual Payment\u0027 modal should show up","duration":315,"startTime":"2022-10-20T19:53:55.511+08:00[Asia/Shanghai]","screenshots":[{"screenshot":"844e3f24b0d8a7f01228f3cd6d119c4f36ef19c4398955c56334e40c6088b4d6.png","timeStamp":1666266835826}],"result":"SUCCESS","precondition":false,"level":0},{"number":25,"description":"When I click on modal \u0027Confirm\u0027 button","duration":4100,"startTime":"2022-10-20T19:53:55.827+08:00[Asia/Shanghai]","screenshots":[{"screenshot":"b704bf334b8551b278476f7802974831e5b4a856d803927fca71ab00712a7071.png","timeStamp":1666266836449},{"screenshot":"c59bd02be88e0011d7da0ecf8acf805056c7275cbd367add73b2d833c6e7d5ca.png","timeStamp":1666266839927}],"result":"SUCCESS","precondition":false,"level":0}],"userStory":{"id":"org.icrc.fadapplic.IRIS.FAD.AccountsPayable.UnbilledPOReceipts","storyName":"Unbilled PO receipts","storyClassName":"org.icrc.fadapplic.IRIS.FAD.AccountsPayable.UnbilledPOReceipts","path":"FAD.AccountsPayable","type":"story"},"featureTag":{"name":"Accounts payable/Unbilled PO receipts","type":"story","displayName":"Accounts payable/Unbilled PO receipts"},"title":"Close unbilled PO receipt","tags":[{"name":"FAD/Accounts payable","type":"feature","displayName":"Accounts payable"},{"name":"Accounts payable/Unbilled PO receipts","type":"story","displayName":"Unbilled PO receipts"},{"name":"FAD","type":"capability","displayName":"FAD"}],"startTime":"2022-10-20T19:51:10.159+08:00[Asia/Shanghai]","duration":169768,"projectKey":"","sessionId":"2713dfeb5b8976868735d96dd2f66c40","driver":"chrome","isManualTestingUpToDate":false,"manual":false,"testSource":"JUnit","result":"SUCCESS"}